Metadata-Version: 2.1
Name: loadinganim
Version: 1.0.1
Summary: A simple terminal loading message
Home-page: UNKNOWN
Author: noidea
Author-email: noidea1238@gmail.com
License: UNKNOWN
Platform: UNKNOWN
Classifier: Programming Language :: Python :: 3
Classifier: License :: OSI Approved :: MIT License
Classifier: Operating System :: OS Independent
Requires-Python: >=3.6
